webhawk/__init__.py
webhawk/src/__init__.py
webhawk/src/__main__.py
webhawk/src/functions.py
webhawk/src/data/config.json
webhawk/src/dependencies/__init__.py
webhawk/src/dependencies/cmsdetector/__init__.py
webhawk/src/dependencies/cmsdetector/cmsdetector.py
webhawk/src/dependencies/linkparser/__init__.py
webhawk/src/dependencies/linkparser/linkparser.py
webhawk/src/dependencies/subdomain/__init__.py
webhawk/src/dependencies/subdomain/subdomains.py
webhawk-1.0.1.dist-info/LICENSE
webhawk-1.0.1.dist-info/METADATA
webhawk-1.0.1.dist-info/WHEEL
webhawk-1.0.1.dist-info/entry_points.txt
webhawk-1.0.1.dist-info/top_level.txt
webhawk-1.0.1.dist-info/RECORD
