Metadata-Version: 2.1
Name: webhawk
Version: 1.0.1
Summary: Web Recon Framework
Home-page: https://github.com/thehackersbrain/webhawk
Author: Gaurav Raj
Author-email: techw803@gmail.com
License: MIT
Keywords: webhawk,web,recon,hacking,python3,python,thehackersbrain,gaurav raj
Platform: UNKNOWN
License-File: LICENSE
Requires-Dist: bs4
Requires-Dist: requests
Requires-Dist: rich
